keygen/__init__.py
keygen/keygen.py
keygen/transforms.py
keygen/utils.py
keygen-0.0.3.dist-info/LICENSE
keygen-0.0.3.dist-info/METADATA
keygen-0.0.3.dist-info/WHEEL
keygen-0.0.3.dist-info/entry_points.txt
keygen-0.0.3.dist-info/top_level.txt
keygen-0.0.3.dist-info/RECORD
