Metadata-Version: 2.1
Name: keygen
Version: 0.0.3
Summary: Keygen for generate keys :)
Home-page: https://github.com/Bobsans/keygen
Author: Bobsans
Author-email: mr.bobsans@gmail.com
Maintainer: Bobsans
Maintainer-email: mr.bobsans@gmail.com
License: Freeware
Keywords: key keygen secure password
Platform: Any
Classifier: Development Status :: 5 - Production/Stable
Classifier: Environment :: Console
Classifier: License :: Freeware
Classifier: Natural Language :: English
Classifier: Programming Language :: Python
Classifier: Programming Language :: Python :: 3
Classifier: Programming Language :: Python :: 3.6
Classifier: Programming Language :: Python :: 3.7
Classifier: Programming Language :: Python :: 3.8
Classifier: Programming Language :: Python :: 3 :: Only
Classifier: Topic :: Utilities
Requires-Python: >=3.6
